[
  {
    "time_scan": "2025-09-24t16:38:26.265483",
    "unidade": "regissol",
    "file_name": "20250902112156465.pdf",
    "codigo_srp": "6206250",
    "nome": "regina mogentali ferreira",
    "especialidade": "cardiologia",
    "nascimento": "1945-12-20T00:00:00",
    "telefone": "+5517992071248",
    "local": "hm mae div amor e provid",
    "profissional": "rafael vinicius cavazzana",
    "chegar_as": "2025-09-24T08:00:00",
    "data_hora_consulta": "2025-10-03T08:20:00"
  },
  {
    "time_scan": "2025-09-24t16:38:26.265483",
    "unidade": "regissol",
    "file_name": "20250902112156465.pdf",
    "codigo_srp": "35096614",
    "nome": "vera lucia pereira crialezi",
    "especialidade": "cardiologia",
    "nascimento": null,
    "telefone": "+5517992682454",
    "local": "hm mae div amor e provid",
    "profissional": "rafael vinicius cavazzana",
    "cns": "702407596912327 898001231573637",
    "chegar_as": "2025-09-24T08:10:00",
    "data_hora_consulta": "2025-10-03T08:30:00"
  },
  {
    "time_scan": "2025-09-24t16:38:26.265483",
    "unidade": "regissol",
    "file_name": "20250902112156465.pdf",
    "codigo_srp": "11318396",
    "nome": "ivo sousa silva",
    "especialidade": "cardiologia",
    "nascimento": "1968-01-29T00:00:00",
    "telefone": "+5517996393069",
    "local": "hm mae div amor e provid",
    "profissional": "rafael vinicius cavazzana",
    "cns": "704108438570050",
    "chegar_as": "2025-09-24T08:20:00",
    "data_hora_consulta": "2025-10-03T08:40:00"
  },
  {
    "time_scan": "2025-09-24t16:38:26.265483",
    "unidade": "regissol",
    "file_name": "20250902112156465.pdf",
    "codigo_srp": "33468039",
    "nome": "patricia portero",
    "especialidade": "cirurgia vascular",
    "nascimento": "1986-03-17T00:00:00",
    "telefone": "+5517982074591 +5517991446824",
    "local": "hm mae div amor e provid",
    "profissional": "fernando guirado neto",
    "cns": "700503157292854 898000047629071",
    "chegar_as": "2025-09-24T13:50:00",
    "data_hora_consulta": "2025-10-01T14:10:00"
  },
  {
    "time_scan": "2025-09-24t16:38:26.265483",
    "unidade": "regissol",
    "file_name": "20250902112156465.pdf",
    "codigo_srp": "20284693",
    "nome": "mercedes elena de sales de moura",
    "especialidade": "cirurgia vascular",
    "nascimento": "1944-07-28T00:00:00",
    "telefone": "+5517996326288 +5517991069112",
    "local": "hm mae div amor e provid",
    "profissional": "fernando guirado neto",
    "cns": "700002236617903 898000104480531",
    "chegar_as": "2025-09-24T14:00:00",
    "data_hora_consulta": "2025-10-01T14:20:00"
  },
  {
    "time_scan": "2025-09-24t16:38:26.265483",
    "unidade": "regissol",
    "file_name": "20250902112156465.pdf",
    "codigo_srp": "12777366",
    "nome": "sonia martins marangon",
    "especialidade": "cirurgia vascular",
    "nascimento": null,
    "telefone": "+5517992640082",
    "local": "hm mae div amor e provid",
    "profissional": "fernando guirado neto",
    "cns": "898001008945287",
    "chegar_as": "2025-09-24T14:10:00",
    "data_hora_consulta": "2025-10-01T14:30:00"
  },
  {
    "time_scan": "2025-09-24t16:38:26.265483",
    "unidade": "regissol",
    "file_name": "20250902112156465.pdf",
    "codigo_srp": "28509282",
    "nome": "nerli maria duarte machado",
    "especialidade": "cirurgia vascular",
    "nascimento": "1960-01-05T00:00:00",
    "telefone": "+5517996780283 +5517991784028",
    "local": "hm mae div amor e provid",
    "profissional": "fernando guirado neto",
    "cns": "203039776330018",
    "chegar_as": "2025-09-24T14:10:00",
    "data_hora_consulta": "2025-10-01T14:30:00"
  },
  {
    "time_scan": "2025-09-24t16:38:26.265483",
    "unidade": "regissol",
    "file_name": "20250902112156465.pdf",
    "codigo_srp": "189749",
    "nome": "alsira amelia da silva",
    "especialidade": "cirurgia vascular",
    "nascimento": "1944-07-23T00:00:00",
    "telefone": "+551792631770",
    "local": "hm mae div amor e provid",
    "profissional": "fernando guirado neto",
    "cns": "706502389956296",
    "chegar_as": "2025-09-24T14:20:00",
    "data_hora_consulta": "2025-10-01T14:40:00"
  },
  {
    "time_scan": "2025-09-24t16:38:26.265483",
    "unidade": "regissol",
    "file_name": "20250902112156465.pdf",
    "codigo_srp": "28992972",
    "nome": "valter jodas gusson",
    "especialidade": "cirurgia vascular",
    "nascimento": "1943-04-27T00:00:00",
    "telefone": "+551732422619 +5517997715139",
    "local": "hm mae div amor e provid",
    "profissional": "fernando guirado neto",
    "cns": "702807101609167",
    "chegar_as": "2025-09-24T14:20:00",
    "data_hora_consulta": "2025-10-01T14:40:00"
  },
  {
    "time_scan": "2025-09-24t16:38:26.265483",
    "unidade": "regissol",
    "file_name": "20250902112156465.pdf",
    "codigo_srp": "11407820",
    "nome": "joice cristiane benevides",
    "especialidade": "cirurgia vascular |",
    "nascimento": "1987-02-21T00:00:00",
    "telefone": "+5517997579584",
    "local": "hm mae div amor e provid",
    "profissional": "fernando guirado neto",
    "cns": "898000081201925",
    "chegar_as": "2025-09-24T14:30:00",
    "data_hora_consulta": "2025-10-01T14:50:00"
  },
  {
    "time_scan": "2025-09-24t16:38:26.265483",
    "unidade": "regissol",
    "file_name": "20250902112156465.pdf",
    "codigo_srp": "12340918",
    "nome": "olga augusto zanquetim",
    "especialidade": "cirurgia vascular",
    "nascimento": "1956-02-01T00:00:00",
    "telefone": "+5517981564986",
    "local": "hm mae div amor e provid",
    "profissional": "fernando guirado neto",
    "cns": "705000434716753",
    "chegar_as": "2025-09-24T14:40:00",
    "data_hora_consulta": "2025-10-01T15:00:00"
  },
  {
    "time_scan": "2025-09-24t16:38:26.265483",
    "unidade": "regissol",
    "file_name": "20250902112156465.pdf",
    "codigo_srp": "22335343",
    "nome": "antonia alves da silva",
    "especialidade": "otorrinolaringologia",
    "nascimento": null,
    "telefone": "+551732535329 +5517991469964",
    "local": "hm mae div amor e provid",
    "profissional": "silvio andrade filho",
    "cns": "707807642757217 898000081260778",
    "chegar_as": "2025-09-24T08:20:00",
    "data_hora_consulta": "2025-10-02T08:40:00"
  },
  {
    "time_scan": "2025-09-24t16:38:26.265483",
    "unidade": "regissol",
    "file_name": "20250902112156465.pdf",
    "codigo_srp": "4090383",
    "nome": "anesia de fatima carmona da silva",
    "especialidade": "otorrinolaringologia",
    "nascimento": "1956-11-27T00:00:00",
    "telefone": "+551796210134 +5517997453416",
    "local": "hm mae div amor e provid",
    "profissional": "silvio andrade filho",
    "cns": "708002801275727",
    "chegar_as": "2025-09-24T08:20:00",
    "data_hora_consulta": "2025-10-02T08:40:00"
  },
  {
    "time_scan": "2025-09-24t16:38:26.265483",
    "unidade": "regissol",
    "file_name": "20250902112156465.pdf",
    "codigo_srp": "22334535",
    "nome": "marlene mariano de lima fornarollis",
    "especialidade": "otorrinolaringologia",
    "nascimento": "1968-12-08T00:00:00",
    "telefone": "+5517991879696",
    "local": "hm mae div amor e provid",
    "profissional": "silvio andrade filho",
    "cns": "700508362197854 898000047625149",
    "chegar_as": "2025-09-24T08:30:00",
    "data_hora_consulta": "2025-10-02T08:50:00"
  },
  {
    "time_scan": "2025-09-24t16:38:26.265483",
    "unidade": "regissol",
    "file_name": "20250902112156465.pdf",
    "codigo_srp": "39451001",
    "nome": "joao miguel rodrigues vieira",
    "especialidade": "otorrinolaringologia",
    "nascimento": "2017-10-06T00:00:00",
    "telefone": "+5517988026419",
    "local": "hm mae div amor e provid",
    "profissional": "silvio andrade filho",
    "cns": "898005812300013",
    "chegar_as": "2025-09-24T08:30:00",
    "data_hora_consulta": "2025-10-02T08:50:00"
  },
  {
    "time_scan": "2025-09-24t16:38:26.265483",
    "unidade": "regissol",
    "file_name": "20250902112156465.pdf",
    "codigo_srp": "11426170",
    "nome": "jose antonio de almeida",
    "especialidade": "otorrinotaringologia",
    "nascimento": "1961-01-08T00:00:00",
    "telefone": "+5517981482163",
    "local": "hm mae div amor e provid",
    "profissional": "silvio andrade filho",
    "cns": "700307968048534",
    "chegar_as": "2025-09-24T08:40:00",
    "data_hora_consulta": "2025-10-02T09:00:00"
  },
  {
    "time_scan": "2025-09-24t16:38:26.265483",
    "unidade": "regissol",
    "file_name": "20250902112156465.pdf",
    "codigo_srp": "30524150",
    "nome": "oscar caetano costa de carvalho neto",
    "especialidade": "otorrinolaringologia ,",
    "nascimento": "1990-01-12T00:00:00",
    "telefone": "+5517992733519 +5517992586888",
    "local": "hm mae div amor e provid",
    "profissional": "silvio andrade filho",
    "cns": "704102129928575",
    "chegar_as": "2025-09-24T08:40:00"
  },
  {
    "time_scan": "2025-09-24t16:38:26.265483",
    "unidade": "regissol",
    "file_name": "20250902112156465.pdf",
    "codigo_srp": "38621641",
    "nome": "julio cesar da silva",
    "especialidade": "cirurgia geral",
    "nascimento": "1971-08-28T00:00:00",
    "telefone": "+5517992830436 +5517991691678",
    "local": "hm mae div amor e provid",
    "profissional": "jose roberto dos santos rodrigues",
    "cns": "708600542119085",
    "chegar_as": "2025-09-24T07:00:00",
    "data_hora_consulta": "2025-10-09T07:20:00"
  },
  {
    "time_scan": "2025-09-24t16:38:26.265483",
    "unidade": "regissol",
    "file_name": "20250902112156465.pdf",
    "codigo_srp": "36589041",
    "nome": "selma carvalho freitas",
    "especialidade": "otorrinolaringologia",
    "nascimento": "1981-09-17T00:00:00",
    "telefone": "+5517992466331 +5517988370136",
    "local": "hm mae div amor e provid",
    "profissional": "silvio andrade filho",
    "cns": "704107472060050",
    "chegar_as": "2025-09-24T07:20:00",
    "data_hora_consulta": "2025-10-09T07:40:00"
  },
  {
    "time_scan": "2025-09-24t16:38:26.265483",
    "unidade": "regissol",
    "file_name": "20250902112156465.pdf",
    "codigo_srp": "38702054",
    "nome": "lara keury carvalho de souyza",
    "especialidade": "otorrinolaringologia",
    "nascimento": "2014-10-04T00:00:00",
    "telefone": "+5517981403606",
    "local": "hm mae div amor e provid",
    "profissional": "silvio andrade filho",
    "cns": "701203047912719",
    "chegar_as": "2025-09-24T07:20:00",
    "data_hora_consulta": "2025-10-09T07:40:00"
  },
  {
    "time_scan": "2025-09-24t16:38:26.265483",
    "unidade": "regissol",
    "file_name": "20250902112156465.pdf",
    "codigo_srp": "6030859",
    "nome": "faustiniano dos santos",
    "especialidade": "otorrinolaringologia",
    "nascimento": null,
    "telefone": "+5517997331837",
    "local": "hm mae div amor e provid",
    "profissional": "silvio andrade f ilho",
    "cns": "701809261639078 801434308679686",
    "chegar_as": "2025-09-24T07:30:00",
    "data_hora_consulta": "2025-10-09T07:50:00"
  },
  {
    "time_scan": "2025-09-24t16:38:26.265483",
    "unidade": "regissol",
    "file_name": "20250902112156465.pdf",
    "codigo_srp": "10306473",
    "nome": "armida crocillo madi .",
    "especialidade": "otorrinolaringologia",
    "nascimento": "1947-07-09T00:00:00",
    "telefone": "+551732426305 +5517991098556",
    "local": "hm mae div amor e provid",
    "profissional": "silvio andrade f ilho",
    "cns": "801434359615170",
    "chegar_as": "2025-09-24T07:30:00",
    "data_hora_consulta": "2025-10-09T07:50:00"
  },
  {
    "time_scan": "2025-09-24t16:38:26.265483",
    "unidade": "regissol",
    "file_name": "20250902112156465.pdf",
    "codigo_srp": "36380235",
    "nome": "luana pereira de oliveira",
    "especialidade": "psiquiatria",
    "nascimento": "2002-06-27T00:00:00",
    "telefone": "+5517992808949 +5517992636636",
    "local": "hm mae div amor e provid",
    "profissional": "michelle macruz peresi",
    "cns": "704703755657830",
    "chegar_as": "2025-09-24T15:50:00",
    "data_hora_consulta": "2025-10-08T16:10:00"
  },
  {
    "time_scan": "2025-09-24t16:38:26.265483",
    "unidade": "regissol",
    "file_name": "20250902112156465.pdf",
    "codigo_srp": "10389275",
    "nome": "bruna camila sales prado",
    "especialidade": "psiquiatria",
    "nascimento": null,
    "telefone": "+5517992175082 +5517988008759",
    "local": "hm mae div amor e provid",
    "profissional": "marina nahas mega",
    "cns": "705007807358853 898000185663216",
    "chegar_as": "2025-09-24T13:50:00",
    "data_hora_consulta": "2025-10-09T14:10:00"
  },
  {
    "time_scan": "2025-09-24t16:38:26.265483",
    "unidade": "regissol",
    "file_name": "20250902112156465.pdf",
    "codigo_srp": "22326446",
    "nome": "social: natalia oliveira figueiredo",
    "especialidade": "psiquiatria",
    "nascimento": null,
    "telefone": "+551732427325 +5517991519115",
    "local": "hm mae div amor e provid",
    "profissional": "julia monteiro baggio montialli",
    "cns": "708408285917467",
    "chegar_as": "2025-09-24T11:50:00",
    "data_hora_consulta": "2025-10-05T12:10:00"
  },
  {
    "time_scan": "2025-09-24t16:38:26.265483",
    "unidade": "regissol",
    "file_name": "20250902112156465.pdf",
    "codigo_srp": "5655825",
    "nome": "maria madalena de santana freires",
    "especialidade": "psiquiatria",
    "nascimento": null,
    "telefone": "+5517988154379 +551788144653 +5517997805403",
    "local": "hm mae div amor e provid",
    "profissional": "michelle macruz peresi",
    "cns": "703605077832637",
    "chegar_as": "2025-09-24T16:10:00",
    "data_hora_consulta": "2025-10-08T16:30:00"
  },
  {
    "time_scan": "2025-09-24t16:38:26.265483",
    "unidade": "regissol",
    "file_name": "20250902112156465.pdf",
    "codigo_srp": "39638084",
    "nome": "valdair alves viana",
    "especialidade": "psiquiatria",
    "nascimento": null,
    "telefone": "+5517988124736",
    "local": "hm mae div amor e provid",
    "profissional": "julia monteiro baggio montialli",
    "cns": "702007342444384",
    "chegar_as": "2025-09-24T12:10:00",
    "data_hora_consulta": "2025-10-05T12:30:00"
  },
  {
    "time_scan": "2025-09-24t16:38:26.265483",
    "unidade": "regissol",
    "file_name": "20250902112156465.pdf",
    "codigo_srp": "4450466",
    "nome": "dirce aparecida sanches",
    "especialidade": "psiquiatria",
    "nascimento": "1952-05-08T00:00:00",
    "telefone": "+5517981363038 +551797028165 +5517991370330",
    "local": "hm mae div amor e provid",
    "profissional": "marina nahas mega",
    "cns": "700005079949400",
    "chegar_as": "2025-09-24T14:10:00",
    "data_hora_consulta": "2025-10-09T14:30:00"
  },
  {
    "time_scan": "2025-09-24t16:38:26.265483",
    "unidade": "regissol",
    "file_name": "20250902112156465.pdf",
    "codigo_srp": "23567633",
    "nome": "ian de melo cumba",
    "especialidade": "psiquiatria",
    "nascimento": "2008-02-11T00:00:00",
    "telefone": "+5517988097936",
    "local": "hm mae div amor e provid",
    "profissional": "marina nahas mega",
    "cns": "704706712127239 898001985443742",
    "chegar_as": "2025-09-24T14:20:00",
    "data_hora_consulta": "2025-10-09T14:40:00"
  },
  {
    "time_scan": "2025-09-24t16:38:26.265483",
    "unidade": "regissol",
    "file_name": "20250902112156465.pdf",
    "codigo_srp": "11932680",
    "nome": "luzia aparecida beijo nunes .",
    "especialidade": "psiquiatria",
    "nascimento": "1996-01-07T00:00:00",
    "telefone": "+5517988097936 +5517988018332",
    "local": "hm mae div amor e provid",
    "profissional": "marina nahas mega",
    "cns": "701406601386633 898050019930285",
    "chegar_as": "2025-09-24T14:40:00",
    "data_hora_consulta": "2025-10-09T15:00:00"
  },
  {
    "time_scan": "2025-09-24t16:38:26.265483",
    "unidade": "regissol",
    "file_name": "20250902112156465.pdf",
    "codigo_srp": "12293737",
    "nome": "neuseli moreira da silva",
    "especialidade": "psiquiatria",
    "nascimento": "1966-01-02T00:00:00",
    "telefone": "+5517981142145 +551732534260 +5517991131074",
    "local": "hm mae div amor e provido",
    "profissional": "marina nahas mega",
    "cns": "702305161631412 898001231900468",
    "chegar_as": "2025-09-24T14:50:00",
    "data_hora_consulta": "2025-10-09T15:10:00"
  },
  {
    "time_scan": "2025-09-24t16:38:26.265483",
    "unidade": "regissol",
    "file_name": "20250902112156465.pdf",
    "codigo_srp": "9984773",
    "nome": "adriano aparecido de souza",
    "especialidade": "psiquiatria",
    "nascimento": "1969-05-05T00:00:00",
    "telefone": "+5517991352235",
    "local": "hm mae div amor e provid",
    "profissional": "marina nahas mega",
    "cns": "700307959962237 898001146797461",
    "chegar_as": "2025-09-24T15:10:00",
    "data_hora_consulta": "2025-10-09T15:30:00"
  },
  {
    "time_scan": "2025-09-24t16:38:26.265483",
    "unidade": "regissol",
    "file_name": "20250902112156465.pdf",
    "codigo_srp": "38944336",
    "nome": "maria jose pereira de souza caciano",
    "especialidade": "psiquiatria",
    "nascimento": "1963-03-09T00:00:00",
    "telefone": "+5517992447520",
    "local": "hm mae div amor e provid",
    "profissional": "julia monteiro baggio montialli",
    "chegar_as": "2025-09-24T12:20:00",
    "data_hora_consulta": "2025-10-05T12:40:00"
  },
  {
    "time_scan": "2025-09-24t16:38:26.265483",
    "unidade": "regissol",
    "file_name": "20250902112156465.pdf",
    "codigo_srp": "4150361",
    "nome": "ana rosa custodio galo da silva",
    "especialidade": "psiquiatria",
    "nascimento": "1973-01-05T00:00:00",
    "telefone": "+5517991068267 +5517991050401",
    "local": "hm mae div amor e provid",
    "profissional": "marina nahas mega",
    "cns": "700500154934259",
    "chegar_as": "2025-09-24T15:20:00"
  },
  {
    "time_scan": "2025-09-24t16:38:26.265483",
    "unidade": "regissol",
    "file_name": "20250902112156465.pdf",
    "codigo_srp": "37271822",
    "nome": "valdir antonio partezani",
    "especialidade": "psiquiatria",
    "nascimento": "1964-01-09T00:00:00",
    "telefone": "+5517996441314",
    "local": "-hm mae div amor e provid",
    "profissional": "marina nahas mega",
    "cns": "705003445298055",
    "chegar_as": "2025-09-24T14:40:00"
  },
  {
    "time_scan": "2025-09-24t16:38:26.265483",
    "unidade": "regissol",
    "file_name": "20250902112156465.pdf",
    "codigo_srp": "22364732",
    "nome": "davi uliana ventura",
    "especialidade": "psiquiatria",
    "nascimento": "2011-12-06T00:00:00",
    "telefone": "+5517981752477",
    "local": "hm mae div amor e provid",
    "profissional": "michelle macruz peresi",
    "cns": "898004026248668",
    "chegar_as": "2025-09-24T08:10:00",
    "data_hora_consulta": "2025-10-14T08:30:00"
  },
  {
    "time_scan": "2025-09-24t16:38:26.265483",
    "unidade": "regissol",
    "file_name": "20250902112156465.pdf",
    "codigo_srp": "11337010",
    "nome": "jean vitor guiraldeli",
    "especialidade": "psiquiatria",
    "nascimento": "1989-04-19T00:00:00",
    "telefone": "+5517992495819 +551792153638 +5517991811502",
    "local": "hm mae div amor e provid",
    "profissional": "julia monteiro baggio montialli",
    "cns": "701009800893698 898000075026653",
    "chegar_as": "2025-09-24T06:50:00",
    "data_hora_consulta": "2025-10-12T07:10:00"
  },
  {
    "time_scan": "2025-09-24t16:38:26.265483",
    "unidade": "regissol",
    "file_name": "20250902112156465.pdf",
    "codigo_srp": "34746530",
    "nome": "arlinda landim da costa marcelino",
    "especialidade": "psiquiatria",
    "nascimento": "1970-03-26T00:00:00",
    "telefone": "+5517997376913 +5511983217122",
    "local": "hm mae div amor e provid",
    "profissional": "julia monteiro baggio montialli",
    "cns": "705604405267715",
    "chegar_as": "2025-09-24T15:10:00",
    "data_hora_consulta": "2025-10-05T15:30:00"
  },
  {
    "time_scan": "2025-09-24t16:38:26.265483",
    "unidade": "regissol",
    "file_name": "20250902112156465.pdf",
    "codigo_srp": "8657410",
    "nome": "ivanete terres ferreira",
    "especialidade": "psiquiatria",
    "nascimento": "1975-04-04T00:00:00",
    "telefone": "+5517996113364 +5517997178497 +5517991444559",
    "local": "hm mae div amor e provid",
    "profissional": "michelle macruz peresi",
    "cns": "200671311600008 702405529736928",
    "chegar_as": "2025-09-24T08:20:00",
    "data_hora_consulta": "2025-10-14T08:40:00"
  },
  {
    "time_scan": "2025-09-24t16:38:26.265483",
    "unidade": "regissol",
    "file_name": "20250902112156465.pdf",
    "codigo_srp": "4800447",
    "nome": "ivone aparecida barbosa",
    "especialidade": "psiquiatria",
    "nascimento": "1967-12-11T00:00:00",
    "telefone": "+5517991283090 +5517996681267",
    "local": "am mae div amor e provid",
    "profissional": "michelle macruz peresi",
    "cns": "700909903639798 898000749092833",
    "chegar_as": "2025-09-24T08:40:00",
    "data_hora_consulta": "2025-10-14T09:00:00"
  },
  {
    "time_scan": "2025-09-24t16:38:26.265483",
    "unidade": "regissol",
    "file_name": "20250902112156465.pdf",
    "codigo_srp": "4288182",
    "nome": "aparecida vicente de paula",
    "especialidade": "psiquiatria",
    "nascimento": "1956-04-09T00:00:00",
    "telefone": "+5517997742773 +5517997742773",
    "local": "hm mae div amor e provid",
    "profissional": "michelle macruz peres",
    "cns": "898001234768609",
    "chegar_as": "2025-09-24T08:50:00",
    "data_hora_consulta": "2025-10-14T09:10:00"
  },
  {
    "time_scan": "2025-09-24t16:38:26.265483",
    "unidade": "regissol",
    "file_name": "20250902112156465.pdf",
    "codigo_srp": "9975662",
    "nome": "ademir de souza braga",
    "especialidade": "psiquiatria",
    "nascimento": "1979-08-12T00:00:00",
    "telefone": "+5517997211321 +5517992224121",
    "local": "hm mae div amor e provid",
    "profissional": "julia monteiro baggio montialli",
    "cns": "704801027354947 898001264892456",
    "chegar_as": "2025-09-24T15:40:00",
    "data_hora_consulta": "2025-10-05T16:00:00"
  },
  {
    "time_scan": "2025-09-24t16:38:26.265483",
    "unidade": "regissol",
    "file_name": "20250902112156465.pdf",
    "codigo_srp": "6344124",
    "nome": "social: sonia maria casagrande zivieri",
    "especialidade": "psiquiatria",
    "nascimento": "1959-02-22T00:00:00",
    "telefone": "+551732535764 +5517991631908",
    "local": "hm mae div amor e provid",
    "profissional": "julia monteiro baggio montialli",
    "cns": "898000081257734",
    "chegar_as": "2025-09-24T15:20:00",
    "data_hora_consulta": "2025-10-05T15:40:00"
  },
  {
    "time_scan": "2025-09-24t16:38:26.265483",
    "unidade": "regissol",
    "file_name": "20250902112156465.pdf",
    "codigo_srp": "12396739",
    "nome": "patricia cesar tobias",
    "especialidade": "psiquiatria",
    "nascimento": "1977-08-01T00:00:00",
    "telefone": "+5517991345756",
    "local": "hm mae div amor e provid",
    "profissional": "michelle macruz peres!",
    "cns": "706002890965841",
    "chegar_as": "2025-09-24T09:10:00",
    "data_hora_consulta": "2025-10-14T09:30:00"
  },
  {
    "time_scan": "2025-09-24t16:38:26.265483",
    "unidade": "regissol",
    "file_name": "20250902112156465.pdf",
    "codigo_srp": "34450114",
    "nome": "marli ferreira dias",
    "especialidade": "psiquiatria",
    "nascimento": "1945-07-08T00:00:00",
    "telefone": "+5517991867880 +5517988270388",
    "local": "hm mae div amor e provid",
    "profissional": "michelle macruz peresi",
    "cns": "700506145296658",
    "chegar_as": "2025-09-24T09:20:00",
    "data_hora_consulta": "2025-10-14T09:40:00"
  },
  {
    "time_scan": "2025-09-24t16:38:26.265483",
    "unidade": "regissol",
    "file_name": "20250902112156465.pdf",
    "codigo_srp": "22354071",
    "nome": "horacio fernandes |",
    "especialidade": "psiquiatria",
    "nascimento": "1954-07-04T00:00:00",
    "telefone": "+5517297068507 +551732428809 +5517997068507",
    "local": "hm mae div amor e provid",
    "profissional": "michelle macruz peresi",
    "cns": "708204173669346 898003220573993",
    "chegar_as": "2025-09-24T09:40:00",
    "data_hora_consulta": "2025-10-14T10:00:00"
  },
  {
    "time_scan": "2025-09-24t16:38:26.265483",
    "unidade": "regissol",
    "file_name": "20250902112156465.pdf",
    "codigo_srp": "11782179",
    "nome": "lucelia fernandes dos santos pereira",
    "especialidade": "psiquiatria",
    "nascimento": "1962-03-17T00:00:00",
    "telefone": "+5517996734876",
    "local": "hm mae div amor e provid",
    "profissional": "michelle macruz peres!",
    "cns": "706301776547579 898001234786127 898003734757128",
    "chegar_as": "2025-09-24T09:50:00",
    "data_hora_consulta": "2025-10-14T10:10:00"
  },
  {
    "time_scan": "2025-09-24t16:38:26.265483",
    "unidade": "regissol",
    "file_name": "20250902112156465.pdf",
    "codigo_srp": "12328599",
    "nome": "nycole lorrane dos santos",
    "especialidade": "psiquiatria",
    "nascimento": "2000-11-16T00:00:00",
    "telefone": "+5517992522565 +5517991309383",
    "local": "hm mae div amor e provid",
    "profissional": "michelle macruz peresi",
    "cns": "708607575394081 898000630497232",
    "chegar_as": "2025-09-24T10:10:00",
    "data_hora_consulta": "2025-10-14T10:30:00"
  },
  {
    "time_scan": "2025-09-24t16:38:26.265483",
    "unidade": "regissol",
    "file_name": "20250902112156465.pdf",
    "codigo_srp": "12663392",
    "nome": "social: rosangela scandiuzzi",
    "especialidade": "psiquiatria",
    "nascimento": "1951-06-04T00:00:00",
    "telefone": "+5517981006978",
    "local": "hm mae div amor e provid",
    "profissional": "michelle macruz peresi",
    "cns": "898002731442745",
    "chegar_as": "2025-09-24T10:20:00",
    "data_hora_consulta": "2025-10-14T10:40:00"
  },
  {
    "time_scan": "2025-09-24t16:38:26.265483",
    "unidade": "regissol",
    "file_name": "20250902112156465.pdf",
    "codigo_srp": "12114717",
    "nome": "maria vitoria gouveia",
    "especialidade": "psiquiatria",
    "nascimento": "2006-07-13T00:00:00",
    "telefone": "+5517981634064 +5517997718335",
    "local": "hm mae div amor e provid",
    "profissional": "michelle macruz peresi",
    "cns": "702102722953293",
    "chegar_as": "2025-09-24T12:40:00",
    "data_hora_consulta": "2025-10-14T13:00:00"
  },
  {
    "time_scan": "2025-09-24t16:38:26.265483",
    "unidade": "regissol",
    "file_name": "20250902112156465.pdf",
    "codigo_srp": "5549595",
    "nome": "priscila fernanda dos reis",
    "especialidade": "psiquiatria",
    "nascimento": "1982-11-30T00:00:00",
    "telefone": "+5517997551756 +5517997718335",
    "local": "hm mae div amor e provid",
    "profissional": "michelle macruz peresi",
    "cns": "708004373896828",
    "chegar_as": "2025-09-24T12:50:00",
    "data_hora_consulta": "2025-10-14T13:10:00"
  },
  {
    "time_scan": "2025-09-24t16:38:26.265483",
    "unidade": "regissol",
    "file_name": "20250902112156465.pdf",
    "codigo_srp": "22343392",
    "nome": "marina dias moura",
    "especialidade": "psiquiatria",
    "nascimento": "1953-07-08T00:00:00",
    "telefone": "+5517991425663 +5517991568450",
    "local": "hm mae div amor e provid",
    "profissional": "julia monteiro baggio montialli",
    "cns": "706705532334010 898001232364640",
    "chegar_as": "2025-09-24T15:50:00",
    "data_hora_consulta": "2025-10-05T16:10:00"
  },
  {
    "time_scan": "2025-09-24t16:38:26.265483",
    "unidade": "regissol",
    "file_name": "20250902112156465.pdf",
    "codigo_srp": "9548729",
    "nome": "angelina maria frazao barbosa",
    "especialidade": "psiquiatria",
    "nascimento": "1964-07-20T00:00:00",
    "telefone": "+551732422772 +5517992074253",
    "local": "hm mae div amor e provid",
    "profissional": "michelle macruz peresi",
    "cns": "700307932364134 898000104432057",
    "chegar_as": "2025-09-24T13:10:00",
    "data_hora_consulta": "2025-10-14T13:30:00"
  },
  {
    "time_scan": "2025-09-24t16:38:26.265483",
    "unidade": "regissol",
    "file_name": "20250902112156465.pdf",
    "codigo_srp": "30256942",
    "nome": "juan pyetro barbosa",
    "especialidade": "psiquiatria",
    "nascimento": "2011-09-22T00:00:00",
    "telefone": "+5517991086487 +5517992074253",
    "local": "hm mae div amor e provid",
    "profissional": "michelle macruz peresi",
    "cns": "706808247562827 801434345378678",
    "chegar_as": "2025-09-24T13:20:00",
    "data_hora_consulta": "2025-10-14T13:40:00"
  },
  {
    "time_scan": "2025-09-24t16:38:26.265483",
    "unidade": "regissol",
    "file_name": "20250902112156465.pdf",
    "codigo_srp": "12944920",
    "nome": "vera lucia dos santos",
    "especialidade": "psiquiatria",
    "nascimento": "1960-08-06T00:00:00",
    "telefone": "+5517992618268",
    "local": "hm mae div amor e provid",
    "profissional": "michelle macruz peres!",
    "cns": "700001301817400",
    "chegar_as": "2025-09-24T13:40:00",
    "data_hora_consulta": "2025-10-14T14:00:00"
  },
  {
    "time_scan": "2025-09-24t16:38:26.265483",
    "unidade": "regissol",
    "file_name": "20250902112156465.pdf",
    "codigo_srp": "4066451",
    "nome": "daniela cristina vieira",
    "especialidade": "psiquiatria",
    "nascimento": "1974-04-14T00:00:00",
    "telefone": "+5517992554580 +5517991806530",
    "local": "hm mae div amor e provid",
    "profissional": "michelle macruz peresi",
    "cns": "706300729519571 898001232178022",
    "chegar_as": "2025-09-24T13:50:00",
    "data_hora_consulta": "2025-10-14T14:10:00"
  },
  {
    "time_scan": "2025-09-24t16:38:26.265483",
    "unidade": "regissol",
    "file_name": "20250902112156465.pdf",
    "codigo_srp": "10749068",
    "nome": "elenice aparecida de souza rodrigues",
    "especialidade": "psiquiatria",
    "nascimento": "1973-11-05T00:00:00",
    "telefone": "+5517981333281 +5517981308331",
    "local": "hm mae div amor e provid",
    "profissional": "julia monteiro baggio montialli",
    "cns": "700306951188035 898005156527428",
    "chegar_as": "2025-09-24T16:10:00",
    "data_hora_consulta": "2025-10-05T16:30:00"
  },
  {
    "time_scan": "2025-09-24t16:38:26.265483",
    "unidade": "regissol",
    "file_name": "20250902112156465.pdf",
    "codigo_srp": "12231189",
    "nome": "nadiny juliana sapionatto",
    "especialidade": "psiquiatria",
    "nascimento": "1992-02-13T00:00:00",
    "telefone": "+5517992352683",
    "local": "hm mae div amor e provid",
    "profissional": "michelle macruz peresi",
    "cns": "707608245047291",
    "chegar_as": "2025-09-24T14:10:00",
    "data_hora_consulta": "2025-10-14T14:30:00"
  },
  {
    "time_scan": "2025-09-24t16:38:26.265483",
    "unidade": "regissol",
    "file_name": "20250902112156465.pdf",
    "codigo_srp": "4302829",
    "nome": "lucia cristina bertasso ramazoto",
    "especialidade": "psiquiatria |",
    "nascimento": "1973-05-03T00:00:00",
    "telefone": "+5517992435757 +5517991400613",
    "local": "hm mae div amor e provid",
    "profissional": "michelle macruz peresi",
    "cns": "704000849716761",
    "chegar_as": "2025-09-24T14:10:00",
    "data_hora_consulta": "2025-10-09T14:30:00"
  },
  {
    "time_scan": "2025-09-24t16:38:26.265483",
    "unidade": "regissol",
    "file_name": "20250902112156465.pdf",
    "codigo_srp": "7225568",
    "nome": "marilene neves de oliveira",
    "especialidade": "psiquiatria",
    "nascimento": "1966-01-23T00:00:00",
    "telefone": "+551732427656 +5517991269688",
    "local": "hm mae div amor e provid",
    "profissional": "michelle macruz peresi",
    "cns": "704200527844190 898000081310244",
    "chegar_as": "2025-09-24T14:20:00",
    "data_hora_consulta": "2025-10-09T14:40:00"
  },
  {
    "time_scan": "2025-09-24t16:38:26.265483",
    "unidade": "regissol",
    "file_name": "20250902112156465.pdf",
    "codigo_srp": "4331242",
    "nome": "rita oliveira neves",
    "especialidade": "psiquiatria",
    "nascimento": "1941-02-04T00:00:00",
    "telefone": "+5517997518033 +551732427656 +5517992114138",
    "local": "hm mae div amor e provid",
    "profissional": "michelle macruz peresi",
    "cns": "700000529810306 898000081202638",
    "chegar_as": "2025-09-24T14:40:00",
    "data_hora_consulta": "2025-10-09T15:00:00"
  },
  {
    "time_scan": "2025-09-24t16:38:26.265483",
    "unidade": "regissol",
    "file_name": "20250902112156465.pdf",
    "codigo_srp": "10538086",
    "nome": "claudete da silva matavelli",
    "especialidade": "psiquiatria",
    "nascimento": "1946-04-28T00:00:00",
    "telefone": "+5517997461591",
    "local": "hm mae div amor e provid",
    "profissional": "michelle macruz peres!",
    "cns": "701003866363497",
    "chegar_as": "2025-09-24T14:50:00",
    "data_hora_consulta": "2025-10-09T15:10:00"
  },
  {
    "time_scan": "2025-09-24t16:38:26.265483",
    "unidade": "regissol",
    "file_name": "20250902112156465.pdf",
    "codigo_srp": "39614072",
    "nome": "silvia matavelli candido dos santos",
    "especialidade": "psiquiatria",
    "nascimento": "1965-09-18T00:00:00",
    "telefone": "+5517981126300 +5517997461591",
    "local": "hm mae div amor e provid",
    "profissional": "michelle macruz peres!",
    "cns": "707408060482074",
    "chegar_as": "2025-09-24T15:10:00",
    "data_hora_consulta": "2025-10-09T15:30:00"
  },
  {
    "time_scan": "2025-09-24t16:38:26.265483",
    "unidade": "regissol",
    "file_name": "20250902112156465.pdf",
    "codigo_srp": "37279112",
    "nome": "wellington luis da silva",
    "especialidade": "psiquiatria",
    "nascimento": "1977-09-07T00:00:00",
    "telefone": "+551732422231 +5517996361240",
    "local": "hm mae div amor e provid",
    "profissional": "michelle macruz peres]",
    "cns": "709602652229276 801434347268675",
    "chegar_as": "2025-09-24T15:20:00",
    "data_hora_consulta": "2025-10-09T15:40:00"
  },
  {
    "time_scan": "2025-09-24t16:38:26.265483",
    "unidade": "regissol",
    "file_name": "20250902112156465.pdf",
    "codigo_srp": "12861667",
    "nome": "valdecir vieira de assis",
    "especialidade": "psiquiatria",
    "nascimento": "1951-09-22T00:00:00",
    "telefone": "+5517288201076 +5517992535009",
    "local": "hm mae div amor e provid",
    "profissional": "michelle macruz peres",
    "cns": "709006865930817",
    "chegar_as": "2025-09-24T15:40:00",
    "data_hora_consulta": "2025-10-09T16:00:00"
  },
  {
    "time_scan": "2025-09-24t16:38:26.265483",
    "unidade": "regissol",
    "file_name": "20250902112156465.pdf",
    "codigo_srp": "33107314",
    "nome": "doralice ribeiro dos santos souza",
    "especialidade": "psiquiatria",
    "nascimento": "1963-11-18T00:00:00",
    "telefone": "+551634156878 +5516992332007",
    "local": "hm mae div amor e provid |",
    "profissional": "michelle macruz peres!",
    "cns": "704509304448819 898000744033278",
    "chegar_as": "2025-09-24T15:50:00",
    "data_hora_consulta": "2025-10-09T16:10:00"
  },
  {
    "time_scan": "2025-09-24t16:38:26.265483",
    "unidade": "regissol",
    "file_name": "20250902112156465.pdf",
    "codigo_srp": "4361599",
    "nome": "maria de lourdes vieira figueiredo",
    "especialidade": "psiquiatria",
    "nascimento": "1961-01-12T00:00:00",
    "telefone": "+551781022601 +5517982021131",
    "local": "hm mae div amor e provid",
    "profissional": "michelle macruz peres!",
    "cns": "708609506874381",
    "chegar_as": "2025-09-24T16:10:00",
    "data_hora_consulta": "2025-10-09T16:30:00"
  },
  {
    "time_scan": "2025-09-24t16:38:26.265483",
    "unidade": "regissol",
    "file_name": "20250902112156465.pdf",
    "codigo_srp": "32166459",
    "nome": "thiago vinicius rocha oteiro",
    "especialidade": "psiquiatria",
    "nascimento": "1988-10-28T00:00:00",
    "telefone": "+5517997889472 +5517982279218",
    "local": "hm mae div amor e provid",
    "profissional": "michelle macruz peresi",
    "cns": "700006275357104 898000634179081",
    "chegar_as": "2025-09-24T16:20:00",
    "data_hora_consulta": "2025-10-09T16:40:00"
  },
  {
    "time_scan": "2025-09-24t16:38:26.265483",
    "unidade": "regissol",
    "file_name": "20250902112156465.pdf",
    "codigo_srp": "5304495",
    "nome": "adriana da silva nery",
    "especialidade": "psiquiatria",
    "nascimento": "1978-07-24T00:00:00",
    "telefone": "+5517988202358",
    "local": "hm mae div amor e provid",
    "profissional": "marina nahas mega",
    "cns": "700205440577028 898002384212925",
    "chegar_as": "2025-09-24T15:20:00",
    "data_hora_consulta": "2025-10-14T15:40:00"
  },
  {
    "time_scan": "2025-09-24t16:38:26.265483",
    "unidade": "regissol",
    "file_name": "20250902112156465.pdf",
    "codigo_srp": "9985039",
    "nome": "adriano cesar de carvalho",
    "especialidade": "psiquiatria",
    "nascimento": "1991-07-03T00:00:00",
    "telefone": "+5517997520391 +5517996242423",
    "local": "hm mae div amor e provid",
    "profissional": "julia monteiro baggio montialli",
    "cns": "702809630973468",
    "chegar_as": "2025-09-24T12:50:00",
    "data_hora_consulta": "2025-10-05T13:10:00"
  },
  {
    "time_scan": "2025-09-24t16:38:26.265483",
    "unidade": "regissol",
    "file_name": "20250902112156465.pdf",
    "codigo_srp": "22042606",
    "nome": "isabela maria brogio",
    "especialidade": "psiquiatria",
    "nascimento": "1994-06-10T00:00:00",
    "telefone": "+551732533225 +5517996293155",
    "local": "hm mae div amor e provid",
    "profissional": "julia monteiro baggio montialli",
    "cns": "700408944524042",
    "chegar_as": "2025-09-24T13:10:00",
    "data_hora_consulta": "2025-10-05T13:30:00"
  },
  {
    "time_scan": "2025-09-24t16:38:26.265483",
    "unidade": "regissol",
    "file_name": "20250902112156465.pdf",
    "codigo_srp": "4173614",
    "nome": "zenir aparecida sanches parra soler",
    "especialidade": "psiquiatria",
    "nascimento": "1964-02-10T00:00:00",
    "telefone": "+551732429814 +5517997237914",
    "local": "hm mae div amor e provid",
    "profissional": "julia monteiro baggio montialli",
    "cns": "898001012046267",
    "chegar_as": "2025-09-24T13:20:00",
    "data_hora_consulta": "2025-10-05T13:40:00"
  },
  {
    "time_scan": "2025-09-24t16:38:26.265483",
    "unidade": "regissol",
    "file_name": "20250902112156465.pdf",
    "codigo_srp": "12274141",
    "nome": "nelci lourdes vieira lima baccan",
    "especialidade": "psiquiatria",
    "nascimento": "1965-12-02T00:00:00",
    "telefone": "+5517991114444 +5517992019662",
    "local": "hm mae div amor e provid",
    "profissional": "julia monteiro baggio montialli",
    "cns": "704609665207425",
    "chegar_as": "2025-09-24T13:40:00",
    "data_hora_consulta": "2025-10-05T14:00:00"
  },
  {
    "time_scan": "2025-09-24t16:38:26.265483",
    "unidade": "regissol",
    "file_name": "20250902112156465.pdf",
    "codigo_srp": "4130073",
    "nome": "suely alves de freitas",
    "especialidade": "psiquiatria",
    "nascimento": "1970-04-10T00:00:00",
    "telefone": "+551732751713 +5517992164090",
    "local": "hm mae div amor e provid",
    "profissional": "michelle macruz peresi",
    "cns": "898000630466558",
    "chegar_as": "2025-09-24T18:50:00",
    "data_hora_consulta": "2025-09-30T19:10:00"
  },
  {
    "time_scan": "2025-09-24t16:38:26.265483",
    "unidade": "regissol",
    "file_name": "20250902112156465.pdf",
    "codigo_srp": "12579274",
    "nome": "reinaldo santos cattai",
    "especialidade": "psiquiatria",
    "nascimento": "1964-01-07T00:00:00",
    "telefone": "+5517992590565",
    "local": "hm mae div amor e provid",
    "profissional": "julia monteiro baggio montialli",
    "cns": "703106366947560 898003265716971",
    "chegar_as": "2025-09-24T13:50:00",
    "data_hora_consulta": "2025-10-05T14:10:00"
  },
  {
    "time_scan": "2025-09-24t16:38:26.265483",
    "unidade": "regissol",
    "file_name": "20250902112156465.pdf",
    "codigo_srp": "37231311",
    "nome": "marcia regina gonzales",
    "especialidade": "psiquiatria",
    "nascimento": "1970-09-27T00:00:00",
    "telefone": "+5517996293155",
    "local": "hm mae div amor e provid",
    "profissional": "julia monteiro baggio montialli",
    "cns": "709804016529795",
    "chegar_as": "2025-09-24T14:10:00",
    "data_hora_consulta": "2025-10-05T14:30:00"
  },
  {
    "time_scan": "2025-09-24t16:38:26.265483",
    "unidade": "regissol",
    "file_name": "20250902112156465.pdf",
    "codigo_srp": "5462526",
    "nome": "antonia bersi de souza dias",
    "especialidade": "psiquiatria",
    "nascimento": "1949-04-10T00:00:00",
    "telefone": "+551721222805 +5517992221638",
    "local": "hm mae div amor e provid",
    "profissional": "julia monteiro baggio montialli",
    "cns": "706103022393760 898000047695822",
    "chegar_as": "2025-09-24T14:20:00",
    "data_hora_consulta": "2025-10-05T14:40:00"
  },
  {
    "time_scan": "2025-09-24t16:38:26.265483",
    "unidade": "regissol",
    "file_name": "20250902112156465.pdf",
    "codigo_srp": "11502545",
    "nome": "jose salomao de oliveira",
    "especialidade": "psiquiairia",
    "nascimento": "1974-11-12T00:00:00",
    "telefone": "+5517981108477",
    "local": "hm mae div amor e provid",
    "profissional": "julia monteiro baggio montialli",
    "cns": "898001242619536",
    "chegar_as": "2025-09-24T14:40:00",
    "data_hora_consulta": "2025-10-05T15:00:00"
  },
  {
    "time_scan": "2025-09-24t16:38:26.265483",
    "unidade": "regissol",
    "file_name": "20250902112156465.pdf",
    "codigo_srp": "4164012",
    "nome": "leonice machado de freitas",
    "especialidade": "psiquiatria",
    "nascimento": "1956-09-21T00:00:00",
    "telefone": "+5517991238131 +5517991755212",
    "local": "hm mae div amor e provid",
    "profissional": "julia monteiro baggio montialli",
    "cns": "898000445839831",
    "chegar_as": "2025-09-24T14:50:00",
    "data_hora_consulta": "2025-10-05T15:10:00"
  },
  {
    "time_scan": "2025-09-24t16:38:26.265483",
    "unidade": "regissol",
    "file_name": "20250902112156465.pdf",
    "codigo_srp": "11366528",
    "nome": "joao guilherme garcia alonso",
    "especialidade": "psiquiatria",
    "nascimento": "2008-11-09T00:00:00",
    "telefone": "+5517992483047",
    "local": "hm mae div amor e provid",
    "profissional": "michelle macruz peresi",
    "cns": "898003964335497",
    "chegar_as": "2025-09-24T07:40:00",
    "data_hora_consulta": "2025-10-14T08:00:00"
  },
  {
    "time_scan": "2025-09-24t16:38:26.265483",
    "unidade": "regissol",
    "file_name": "20250902112156465.pdf",
    "codigo_srp": "37663057",
    "nome": "sabrina gianini de oliveira",
    "especialidade": "psiquiatria",
    "nascimento": "1994-07-22T00:00:00",
    "telefone": "+5517992107043",
    "local": "hm mae div amor e provid",
    "profissional": "michelle macruz peresi",
    "cns": "700300925660134 801434344593168",
    "chegar_as": "2025-09-24T07:50:00",
    "data_hora_consulta": "2025-10-14T08:10:00"
  },
  {
    "time_scan": "2025-09-24t16:38:26.265483",
    "unidade": "regissol",
    "file_name": "20250902112156465.pdf",
    "codigo_srp": "32302041",
    "nome": "marcelo relvas ornelas",
    "especialidade": "psiquiatria",
    "nascimento": "2016-12-21T00:00:00",
    "telefone": "+5517981564506",
    "local": "hm mae div amor e provid",
    "profissional": "marina nahas mega",
    "cns": "704105154644774 898005147277821",
    "chegar_as": "2025-09-24T12:40:00",
    "data_hora_consulta": "2025-10-13T13:00:00"
  },
  {
    "time_scan": "2025-09-24t16:38:26.265483",
    "unidade": "regissol",
    "file_name": "20250902112156465.pdf",
    "codigo_srp": "38900748",
    "nome": "emelyn vitoria soares dos anjos",
    "especialidade": "psiquiatria",
    "nascimento": "2011-01-05T00:00:00",
    "telefone": "+5517992538991",
    "local": "hm mae div amor e provid",
    "profissional": "marina nahas mega",
    "cns": "898003917372683",
    "chegar_as": "2025-09-24T14:50:00",
    "data_hora_consulta": "2025-10-14T15:10:00"
  },
  {
    "time_scan": "2025-09-24t16:38:26.265483",
    "unidade": "regissol",
    "file_name": "20250902112156465.pdf",
    "codigo_srp": "37365918",
    "nome": "ana luiza monteiro e",
    "especialidade": "psiquiatria",
    "nascimento": "2006-08-22T00:00:00",
    "telefone": "+5517992614045 +5517991829227",
    "local": "hm mae div amor e provid",
    "profissional": "marina nahas mega",
    "cns": "706304714250974",
    "chegar_as": "2025-09-24T15:10:00",
    "data_hora_consulta": "2025-10-14T15:30:00"
  },
  {
    "time_scan": "2025-09-24t16:38:26.265483",
    "unidade": "regissol",
    "file_name": "20250902112156465.pdf",
    "codigo_srp": "8232950",
    "nome": "jose germano assumpcao filho |",
    "especialidade": "psiquiatria",
    "nascimento": "1961-10-11T00:00:00",
    "telefone": "+551733435380",
    "local": "hm mae div amor e provid",
    "profissional": "julia monteiro baggio montialli",
    "cns": "201401103770001 702607760062147",
    "chegar_as": "2025-09-24T12:40:00",
    "data_hora_consulta": "2025-10-05T13:00:00"
  },
  {
    "time_scan": "2025-09-24t16:38:26.265483",
    "unidade": "regissol",
    "file_name": "20250902112156465.pdf",
    "codigo_srp": "35548171",
    "nome": "antonio crepaldi",
    "especialidade": "psiquiatria",
    "nascimento": "1954-09-21T00:00:00",
    "telefone": "+5517997917093",
    "local": "hm mae div amor e provid",
    "profissional": "michelle macruz peresi",
    "cns": "700603948368065",
    "chegar_as": "2025-09-24T16:20:00",
    "data_hora_consulta": "2025-10-08T16:40:00"
  },
  {
    "time_scan": "2025-09-24t16:38:26.265483",
    "unidade": "regissol",
    "file_name": "20250902112156465.pdf",
    "codigo_srp": "13918448",
    "nome": "rildo rodrigues de oliveira",
    "especialidade": "psiquiatria",
    "nascimento": "1966-03-23T00:00:00",
    "telefone": "+5517992591637",
    "local": "hm mae div amor e provid",
    "profissional": "michelle macruz peresi",
    "cns": "702408006276924 898001242673913",
    "chegar_as": "2025-09-24T12:50:00",
    "data_hora_consulta": "2025-10-09T13:10:00"
  },
  {
    "time_scan": "2025-09-24t16:38:26.265483",
    "unidade": "regissol",
    "file_name": "20250902112156465.pdf",
    "codigo_srp": "21889833",
    "nome": "alice pinto dos santos",
    "especialidade": "psiquiatria",
    "nascimento": "1928-09-16T00:00:00",
    "telefone": "+551732431498 +5517992304040",
    "local": "hm mae div amor e provid",
    "profissional": "michelle macruz peresi",
    "cns": "708000394652924",
    "chegar_as": "2025-09-24T13:10:00",
    "data_hora_consulta": "2025-10-09T13:30:00"
  },
  {
    "time_scan": "2025-09-24t16:38:26.265483",
    "unidade": "regissol",
    "file_name": "20250902112156465.pdf",
    "codigo_srp": "4277045",
    "nome": "andreia joana cranchi paschoal",
    "especialidade": "psiquiatria",
    "nascimento": "1978-12-27T00:00:00",
    "telefone": "+5517981065672",
    "local": "-hm mae div amor e provid",
    "profissional": "michelle macruz peresi",
    "cns": "704007856328069 898000080184725",
    "chegar_as": "2025-09-24T13:50:00",
    "data_hora_consulta": "2025-10-09T14:10:00"
  }
]